pysaj/__init__.py
pysaj-0.0.16.dist-info/DESCRIPTION.rst
pysaj-0.0.16.dist-info/METADATA
pysaj-0.0.16.dist-info/RECORD
pysaj-0.0.16.dist-info/WHEEL
pysaj-0.0.16.dist-info/metadata.json
pysaj-0.0.16.dist-info/top_level.txt
