Metadata-Version: 2.1
Name: pysaj
Version: 0.0.16
Summary: Library to communicate with SAJ inverters
Home-page: https://github.com/fredericvl/pysaj
Author: fredericvl
Author-email: frederic.van.linthoudt@gmail.com
License: UNKNOWN
Platform: UNKNOWN
Classifier: Programming Language :: Python :: 3
Classifier: License :: OSI Approved :: Apache Software License
Classifier: Operating System :: OS Independent
Requires-Python: >=3.6
